{
    "document-repository": {
        "title": "दस्तावेज़"
    },
    "document-repository.menus": {
        "leftnav.item": "दस्तावेज़",
        "topbar.item": "दस्तावेज़ रिपॉजिटरी"
    },
    "document-repository.error": {
        "invalidData": ""
    },
    "document-repository.comp.main": {
        "title": "अवलोकन"
    },
    "document-repository.comp.info": {
        "title": "जानकारी",
        "docRepoId": "रिपोजिटरी आईडी:",
        "docRepoName": "दस्तावेज़ रिपॉजिटरी नाम:",
        "modified.label": "संशोधित तिथि",
        "assignee.label": "असाइन करने के लिए",
        "owningGroup.label": "मालिकाना समूह",
        "description.label": "विवरण"
    },
    "document-repository.comp.actions": {
        "title": "क्रियाएं",
        "restrict": "प्रतिबंधित करें?",
        "subscribe.button": "सदस्यता लें",
        "unsubscribe.button": "सदस्यता रद्द करें",
        "delete.button": "रिपॉजिटरी हटाएं",
        "confirm.delete.documentRepository.msg": "यह क्रिया पूरे रिपॉजिटरी को हटा देगा। क्या आप वाकई आगे बढ़ना चाहते हैं?"
    },
    "document-repository.comp.details": {
        "title": "विवरण",
        "informSaved": "दस्तावेज़ भंडार विवरण सहेजे गए",
        "table.columns": {
            "title": "विवरण",
            "modified": "अंतिम संशोधित तारीख",
            "modifier": "उपयोगकर्ता अंतिम संशोधित"
        }
    },
    "document-repository.comp.documents": {
        "title": "दस्तावेज़",
        "sendEmail": "ईमेल भेजें",
        "filterInputPlaceholder": "फ़िल्टर",
        "searchInputPlaceholder": "खोज",
        "newTask": "नया कार्य"
    },
    "document-repository.comp.participants": {
        "title": "प्रतिभागियों",
        "table.columns": {
            "type": "प्रकार",
            "name": "नाम"
        },
        "dialogUserPicker": {
            "header": "उपयोगकर्ता चुनें",
            "table.columns": {
                "name": "नाम",
                "type": "प्रकार",
                "title": "शीर्षक",
                "id": "उपयोगकर्ता नाम"
            }
        },
        "dialogGroupPicker": {
            "header": "समूह चुनें",
            "table.columns": {
                "name": "नाम"
            }
        }
    },
    "document-repository.comp.notes": {
        "title": "नोट्स",
        "table.columns": {
            "note": "ध्यान दें",
            "created": "बनाया था",
            "creator": "लेखक"
        }
    },
    "document-repository.comp.references": {
        "title": "संदर्भ",
        "table.columns": {
            "targetName": "संख्या",
            "parentName": "माता-पिता",
            "targetTitle": "शीर्षक",
            "modified": "संशोधित",
            "targetType": "संदर्भ प्रकार",
            "status": "स्थिति"
        },
        "message": {
            "delete": {
                "success": "hi_Reference deleted successfully",
                "error": "hi_Error deleting reference"
            }
        }
    },
    "document-repository.comp.history": {
        "title": "इतिहास",
        "table.columns": {
            "eventType": "कार्यक्रम नाम",
            "eventDate": "तारीख",
            "userId": "उपयोगकर्ता"
        }
    },
    "document-repository.comp.tags": {
        "title": "टैग",
        "table.columns": {
            "tag": "टैग",
            "created": "बनाया था",
            "createdBy": "के द्वारा बनाई गई"
        },
        "modal": {
            "title": "टैग",
            "search": "टैग के लिए खोजें",
            "buttons": {
                "cancel": "रद्द करना",
                "ok": "टैग जोड़ो"
            }
        },
        "message": {
            "tagExists": "उस नाम या वर्णन या टेक्स्ट से पहले से मौजूद है",
            "tagAssociated": "पहले से जुड़े हुए हैं",
            "delete": {
                "success": "टैग सफलतापूर्वक हटाया गया",
                "error": "टैग हटाने में त्रुटि"
            }
        }
    },
    "document-repository.comp.referenceSearchGrid": {
        "title": "संदर्भ खोज"
    },
    "document-repository.comp.addreference": {
        "title": "संदर्भ जोड़ें",
        "cancelButton": "रद्द करना",
        "confirmButton": "जोड़ना",
        "search": {
            "placeholder": "मामले, शिकायत, फ़ाइल, कार्य के लिए खोजें",
            "btn": "खोज"
        },
        "grid": {
            "columns": {
                "id": "ईद",
                "name": "नाम",
                "type": "प्रकार",
                "title": "शीर्षक",
                "parent": "माता-पिता",
                "assignee": "संपत्ति-भागी",
                "modified": "संशोधित"
            }
        }
    },
    "document-repository.comp.assigneePickerModal": {
        "title": "नियुक्त करें बदलें",
        "assigneeNamelabel": "असाइन का नाम",
        "btnCancelText": "रद्द करना",
        "btnSaveText": "बचाना",
        "searchAssigneeHeader": "निदान खोजें"
    },
    "document-repository.comp.groupPickerModal": {
        "title": "समूह बदलें",
        "groupNamelabel": "समूह का नाम",
        "btnCancelText": "रद्द करना",
        "btnSaveText": "बचाना",
        "searchGroupHeader": "खोज समूह"
    },
    "document-repository.userOrGroupSearch": {
        "id": "userSearch",
        "title": "उपयोगकर्ता / समूह खोज",
        "search": {
            "btn": "खोज",
            "placeholder": "उपयोगकर्ता या समूह खोजें"
        },
        "cancelButton": "रद्द करना",
        "confirmButton": "की पुष्टि करें",
        "assigneeGridColumns": {
            "name": "नाम",
            "type": "प्रकार",
            "title": "शीर्षक",
            "username": "उपयोगकर्ता नाम"
        }
    },
    "document-repository.newRepository": {
        "title": "रिपॉजिटरी बनाएं",
        "assigneeLabel": "संपत्ति-भागी",
        "owningGroupLabel": "मालिकाना समूह",
        "assignee.placeholder": "निदान खोजें",
        "saveButton": "रिपॉजिटरी बनाएं",
        "cancelButton": "रद्द करना",
        "nameLabel": "नाम",
        "name.placeholder": "नाम दर्ज",
        "descriptionLabel": "विवरण",
        "description.placeholder": "विवरण दर्ज करें",
        "searchUser": "उपयोगकर्ता और समूह खोजें",
        "cancelBtn": "रद्द करना",
        "okBtn": "ठीक",
        "search-placeholder": "उपयोगकर्ता और समूह खोजें",
        "personalRepository": "मेरे दस्तावेज"
    },
    "document-repository.dialogUserPicker": {
        "table.columns.name": "नाम",
        "table.columns.type": "प्रकार",
        "table.columns.title": "शीर्षक",
        "table.columns.id": "उपयोगकर्ता नाम"
    },
    "document-repository.tree": {
        "nodeTypes": {
            "details.label": "विवरण",
            "documents.label": "दस्तावेज़",
            "participants.label": "प्रतिभागियों को",
            "tags.label": "टैग",
            "references.label": "सन्दर्भ",
            "notes.label": "टिप्पणियाँ",
            "history.label": "इतिहास"
        },
        "filters": {
            "iHaveCreated": "सभी मैंने बनाया है",
            "iAmFollowing": "सभी मैं अनुसरण कर रहा हूँ",
            "noFilter": "(फ़िल्टर नहीं)"
        },
        "sorters": {
            "dateAsc": "कक्रमबद्ध करें दिनांक ए एस सी",
            "dateDesc": "क्रमबद्ध करें दिनांक वर्णन",
            "idAsc": "सॉर्ट रिपॉजिटरी आईडी एएससी",
            "idDesc": "कसॉर्ट रिपॉजिटरी आईडी डेस्क",
            "nameAsc": "सॉर्ट इन एएनएससी एसी",
            "noSort": "(कोई सॉर्ट नहीं)"
        }
    }
}
