{
    "complaints": {
        "title": "Complaints",
        "progressNoComplaint": "[ No complaint data ]",
        "progressLoading": "Loading complaint ",
        "progressError": "Failed to load complaint "
    },
    "complaints.menus": {
        "leftnav.item": "Complaints",
        "topbar.item": "Complaint"
    },
    "complaints.comp.main": {
        "title": "Overview"
    },
    "complaints.comp.info": {
        "title": "Info",
        "complaintId": "Complaint id:",
        "complaintNumber": "Complaint ID:",
        "courtRoomName": "Court Room Name:",
        "type.label": "Type",
        "created.label": "Created Date",
        "priority.label": "Priority",
        "assignee.label": "Assigned To",
        "owningGroup.label": "Owning Group",
        "dueDate.label": "Due Date",
        "alertMessage": "Due date must be after the create date "
    },
    "complaints.comp.actions": {
        "title": "Actions",
        "restrict": "Restrict?",
        "new.button": "New Complaint",
        "close.button": "Close Complaint",
        "subscribe.button": "Subscribe",
        "unsubscribe.button": "Unsubscribe",
        "claim.button": "Claim",
        "unclaim.button": "Unclaim"
    },
    "complaints.comp.details": {
        "title": "Details",
        "informSaved": "Complaint details saved",
        "table.columns": {
            "title": "Details",
            "modified": "Date Last Modified",
            "modifier": "User Last Modified"
        }
    },
    "complaints.comp.documents": {
        "title": "Documents",
        "sendEmail": "Send Email",
        "filterInputPlaceholder": "Filter",
        "searchInputPlaceholder": "Search",
        "menu": {
            "forms": {
                "rptInvestigation%": "Report of Investigation"
            },
            "correspondences": {
                "correspondenceInvitation%": "Correspondence Invitation",
                "approvalLetter%": "Complaint Approval Letter",
                "generalRelease%": "General Release",
                "medicalRelease%": "Medical Release",
                "clearanceGranted%": "Clearance Granted",
                "clearanceDenied%": "Clearance Denied",
                "witnessInterview%": "Witness Interview Request",
                "witnessInterview2%": "Witness Interview Request-2.0"
            }
        },
        "newTask": "New Task"
    },
    "complaints.comp.people": {
        "title": "People",
        "table.columns": {
            "type": "Role",
            "firstName": "FirstName",
            "lastName": "LastName",
            "organization": "Organization",
            "phone": "Phone",
            "location": "Location"
        }
    },
    "complaints.comp.organizations": {
        "title": "Organizations",
        "table.columns": {
            "name": "Organization Name",
            "associationType": "Role",
            "type": "Organization Type",
            "identification": "ID",
            "value": "Organization",
            "contact": "Primary Contact",
            "phone": "Phone",
            "location": "Location"
        },
        "actions": {
            "delete": "Delete",
            "setPrimary": "Set as Primary",
            "addNew": "Add New",
            "addExisting": "Add New"
        }
    },
    "complaints.comp.participants": {
        "title": "Participants",
        "table.columns": {
            "type": "Type",
            "name": "Name"
        },
        "dialogUserPicker": {
            "header": "Choose User",
            "table.columns": {
                "name": "Name",
                "type": "Type",
                "title": "Title",
                "id": "Username"
            }
        },
        "dialogGroupPicker": {
            "header": "Choose Group",
            "table.columns": {
                "name": "Name"
            }
        }
    },
    "complaints.comp.addresses": {
        "title": "Locations",
        "table.columns": {
            "type": "Type",
            "streetAddress": "Address 1",
            "streetAddress2": "Address 2",
            "city": "City",
            "state": "State",
            "zip": "Zip",
            "country": "Country",
            "created": "Date Added",
            "creator": "Added By",
            "modified": "Last Modified",
            "modifier": "Modified By"
        },
        "actions": {
            "addNew": "Add New",
            "map": "Map"
        },
        "modal": {
            "addAddress": "Add Location",
            "editAddress": "Edit Record",
            "type.label": "Address Type",
            "type.placeholder": "Enter Address Type",
            "streetAddress.label": "Address 1",
            "streetAddress.placeholder": "Enter Address 1",
            "streetAddress2.label": "Address 2",
            "streetAddress2.placeholder": "Enter Address 2",
            "city.label": "City",
            "city.placeholder": "Enter City",
            "zip.label": "Zip",
            "zip.placeholder": "Enter Zip",
            "state.label": "State",
            "state.placeholder": "Enter State",
            "country.label": "Country",
            "country.placeholder": "Enter Country",
            "btnCancel.text": "Cancel",
            "btnOk.text": "Save Location",
            "setPrimary": "Set as Primary?",
            "yes": "Yes",
            "no": "No"
        }
    },
    "complaints.comp.notes": {
        "title": "Notes",
        "table.columns": {
            "note": "Note",
            "created": "Created",
            "creator": "Author"
        }
    },
    "complaints.comp.tasks": {
        "title": "Tasks",
        "table.columns": {
            "title": "Title",
            "assignee": "Assignee",
            "created": "Created",
            "priority": "Priority",
            "due": "Due",
            "status": "Status"
        },
        "table.overdue.tooltip": "Task is Overdue",
        "table.deadline.tooltip": "Deadline is Approaching"
    },
    "complaints.comp.references": {
        "title": "References",
        "table.columns": {
            "targetName": "Number",
            "targetTitle": "Title",
            "targetType": "Type",
            "assignee": "Assignee",
            "modified": "Modified",
            "status": "Status",
            "parentName": "Parent Name"
        }
    },
    "complaints.comp.history": {
        "title": "History",
        "table.columns": {
            "eventType": "Event Name",
            "eventDate": "Date",
            "userId": "User"
        }
    },
    "complaints.comp.time": {
        "title": "Time",
        "table.columns": {
            "name": "Form Name",
            "user": "User",
            "tally": "Total Hours",
            "cost": "Total Cost",
            "modified": "Modified Date",
            "status": "Status"
        },
        "formNamePrefix": "Timesheet"
    },
    "complaints.comp.cost": {
        "title": "Cost",
        "table.columns": {
            "name": "Form Name",
            "user": "User",
            "tally": "Total Cost",
            "modified": "Modified Date",
            "status": "Status"
        },
        "formNamePrefix": "Costsheet"
    },
    "complaints.comp.tags": {
        "title": "Tags",
        "table.columns": {
            "tag": "Tag",
            "created": "Created",
            "createdBy": "Created By"
        },
        "modal": {
            "title": "Tag",
            "search": "Search for Tag",
            "placeholder": "Add tag",
            "buttons": {
                "cancel": "Cancel",
                "ok": "Add Tag"
            }
        },
        "message": {
            "tagExists": "Tag with that name or description or text already exists",
            "tagAssociated": "already associated",
            "delete": {
                "success": "Tag deleted successfully",
                "error": "Error deleting tag"
            }
        }
    },
    "complaints.comp.calendar": {
        "title": "Calendar",
        "infoMessage": "Calendar Integration Configuration Not Enabled"
    },
    "complaints.comp.referenceSearchGrid": {
        "title": "Reference Search"
    },
    "complaints.comp.addreference": {
        "title": "Add Reference",
        "cancelButton": "Cancel",
        "confirmButton": "Add",
        "search": {
            "placeholder": "Search for case, complaint, file, task",
            "btn": "Search"
        },
        "grid": {
            "columns": {
                "id": "Id",
                "name": "Name",
                "type": "Type",
                "title": "Title",
                "parent": "Parent",
                "assignee": "Assignee",
                "modified": "Modified"
            }
        }
    },
    "complaints.comp.assigneePickerModal": {
        "title": "Change Assignee",
        "assigneeNamelabel": "Assignee Name",
        "btnCancelText": "Cancel",
        "btnSaveText": "Save",
        "searchAssigneeHeader": "Search Assignee"
    },
    "complaints.comp.groupPickerModal": {
        "title": "Change Group",
        "groupNamelabel": "Group Name",
        "btnCancelText": "Cancel",
        "btnSaveText": "Save",
        "searchGroupHeader": "Search Group"
    },
    "complaints.comp.approvalRouting": {
        "title": "Approvers",
        "addNewTooltip": "Add new approver",
        "noBuckslipMessage": "No Data",
        "processInitialize.successfull": "Process Initialized",
        "processInitialize.fail": "Process Not Initialized",
        "processWithdraw.successfull": "Process Withdrawn",
        "processWithdraw.fail": "Process Not Withdrawn",
        "businessProcessUpdate.successfull": "Approval Routing Updated",
        "businessProcessUpdate.fail": "Approval Routing Not Updated",
        "button": {
            "save.tooltip": "Save Changes",
            "initiate": "Initiate",
            "withdraw": "Withdraw",
            "initiate.tooltip": "Initiate Task",
            "withdraw.tooltip": "Withdraw Task"
        },
        "checkbox": {
            "nonConcurEndsApprovalCycle": "Non-concur ends the approval cycle"
        },
        "table.columns": {
            "assignee": "Assignee",
            "owningGroup": "Owning Group",
            "subject": "Subject",
            "details": "Details",
            "dueDate": "Due Date",
            "status": "Status",
            "addedBy": "Added By"
        },
        "assigne.none": "None",
        "assignee.label": "Assignee",
        "owningGroup.label": "Owning Group",
        "priority.label": "Priority",
        "startDate.label": "Start Date",
        "dueDate.label": "Due Date",
        "state.label": "State",
        "future.task.modal": {
            "title": "New Future Task",
            "assignee": "Assignee",
            "owningGroup": "Owning Group",
            "subject.label": "Subject",
            "subject.placeholder": "Enter future case subject",
            "details.label": "Details",
            "cancel.button": "Cancel",
            "save.button": "Save"
        }
    },
    "complaints.comp.pastApprovals": {
        "title": "Past Approvers",
        "noBuckslipMessage": "No Data",
        "table.columns": {
            "approvalDate": "Approval Date",
            "approverId": "Approver",
            "approverFullName": "Approver",
            "approverDecision": "Approver Decision"
        }
    },
    "complaints.comp.billing": {
        "title": "Billing",
        "table.columns": {
            "item": "Item #",
            "description": "Description",
            "amount": "Amount",
            "total": "Total: ",
            "buttons": {
                "listInvoices": "List Invoices",
                "emailInvoice": "Email Invoice",
                "generateInvoice": "Generate Invoice"
            }
        },
        "modal": {
            "title": "Add Billing Item",
            "cancel.btn": "Cancel",
            "save.btn": "Save",
            "billingItems.title": "Billing items for"
        },
        "invoice": {
            "title": "Invoices",
            "table.columns": {
                "invoiceNumber": "Invoice Number",
                "status": "Status",
                "creator": "Creator",
                "created": "Created",
                "view": "View"
            }
        },
        "amount.title": "Please enter billing amount",
        "description.title": "Please enter billing description"
    },
    "complaints.comp.closeComplaint": {
        "title": "Close Complaint",
        "info": "Incident Information",
        "description.label": "Description",
        "infoMessage": "Enter in your overall concern and complaint. Please be very specific as to names, places, times, dates, reasons and outcomes.",
        "complaintTitle": "Complaint Title",
        "information": {
            "title": "Close Complaint Information",
            "close.date": "Complaint Close Date",
            "complaint.number": "Complaint Number",
            "complaint.disposition": "Complaint Disposition"
        },
        "add.existing.case": {
            "title": "Add Existing Case",
            "search": "Search",
            "case": {
                "number": "Enter Case Number",
                "title": "Case Title",
                "date": "Case Creation Date",
                "priority": "Case Priority"
            }
        },
        "refer.external": {
            "title": "Refer External",
            "name": "Name of Agency",
            "date": "Referral Date",
            "contact": {
                "title": "Contact",
                "name": "Contact Name",
                "type": "Type",
                "value": "Value"
            }
        },
        "approver": {
            "placeholder": "Select Approver",
            "label": "Approver",
            "addAnother": "Add another",
            "remove": "Remove Approver",
            "pickerModal.header": "User/Group Search",
            "owningGroup": "Owning Group"
        },
        "cancelButton": "Cancel",
        "saveButton": "Save Complaint"
    },
    "complaints.comp.newComplaint": {
        "title": "New Complaint",
        "info": "Incident Information",
        "infoMessage": "Enter in your overall concern and complaint. Please be very specific as to names, places, times, dates, reasons and outcomes.",
        "complaintTitle": "Complaint Title",
        "complaintTitle.placeholder": "Enter Complaint Title",
        "incidentCategory": "Incident Category",
        "initiator": "Initiator",
        "initiator.placeholder": "Select Initiator",
        "complaintDesc": "Complaint Description",
        "priority": "Priority",
        "incidentDate": "Incident Date",
        "incidentDate.placeholder": "Select Incident Date",
        "incidentDate.close.button": "Close",
        "complaintTag": "Complaint Tag",
        "complaintTag.placeholder": "Enter Complaint Tag",
        "frequency": "Frequency",
        "location": {
            "title": "Location",
            "addressType": "Type",
            "streetAddress": "Address",
            "streetAddress.placeholder": "Enter Street Address",
            "city": "City",
            "city.placeholder": "Enter City",
            "state": "State",
            "state.placeholder": "Enter State",
            "country": "Country",
            "zip": "Zip Code",
            "zip.placeholder": "Enter Zip Code",
            "dateCreated": "Date added",
            "creator": "Added By",
            "creator.placeholder": "Enter Creator"
        },
        "people": {
            "title": "People",
            "selectPerson.placeholder": "Search existing Person",
            "personType": "Person Type"
        },
        "participants": {
            "title": "Participants",
            "owningGroup": "Owning Group",
            "owningGroup.info": "The Owning Group can be chosen only through the Owner field",
            "selectParticipant.placeholder": "Select Participant",
            "participantType": "Participant Type"
        },
        "cancelButton": "Cancel",
        "saveButton": "Save Complaint",
        "removeButton": "Remove",
        "addButton": "Add Another"
    },
    "complaints.userOrGroupSearch": {
        "id": "userSearch",
        "title": "User/Group Search",
        "search": {
            "btn": "Search",
            "placeholder": "Search for the user or group."
        },
        "cancelButton": "Cancel",
        "confirmButton": "Confirm",
        "assigneeGridColumns": {
            "name": "Name",
            "type": "Type",
            "title": "Title",
            "username": "Username"
        }
    },
    "complaints.dialogObjectPicker": {
        "header": "Search for document",
        "table.columns": {
            "name": "Name",
            "type": "Type",
            "title": "Title",
            "id": "ID"
        }
    },
    "complaints.tree": {
        "nodeTypes": {
            "details.label": "Details",
            "locations.label": "Locations",
            "people.label": "People",
            "organizations.label": "Organizations",
            "documents.label": "Documents",
            "participants.label": "Participants",
            "notes.label": "Notes",
            "tasks.label": "Tasks",
            "references.label": "References",
            "history.label": "History",
            "time.label": "Time",
            "cost.label": "Cost",
            "tags.label": "Tags",
            "calendar.label": "Calendar",
            "approvalRouting.label": "Approval Routing",
            "billing.label": "Billing"
        },
        "filters": {
            "opened": "All Open Complaints",
            "iHaveCreated": "All I've Created",
            "iAmAssigned": "All I'm Assigned",
            "iAmFollowing": "All I'm Following",
            "closedNoFurtherAction": "All Closed No Further Action",
            "closedReferExternal": "All Closed Refer External",
            "closedOpenInvestigation": "All Closed Open Investigation",
            "noFilter": "(No Filter)"
        },
        "sorters": {
            "incidentDateAsc": "Sort Incident Date Asc",
            "incidentDateDesc": "Sort Incident Date Desc",
            "createdDateAsc": "Sort Created Date Asc",
            "createdDateDesc": "Sort Created Date Desc",
            "nameAsc": "Sort By Name Asc",
            "noSort": "(No Sort)"
        }
    },
    "changes": {
        "object_replaced": {
            "complaint": {
                "defaultAddress": "Default Address Changed"
            }
        },
        "value_changed": {
            "complaint": {
                "details": "Complaint - Details Changed",
                "complaintTitle": "Complaint - Title Changed",
                "complaintType": "Complaint - Type Changed",
                "priority": "Complaint - Priority Changed",
                "status": "Complaint - Status Changed",
                "complaintNumber": "Complaint - Number Changed",
                "dueDate": "Complaint - Due Date Changed",
                "tag": "Complaint - Tag Changed",
                "modifier": "Complaint - Modifier Changed",
                "personAssociations.personAssociation.personType": "Person Association - Type Changed",
                "organizationAssociations.organizationAssociation.associationType": "Organization Association - Type Changed",
                "addresses.address": {
                    "city": "Address - City Changed",
                    "zip": "Address - Zip Code Changed",
                    "streetAddress": "Address - Street Changed",
                    "streetAddress2": "Address - Street2 Changed",
                    "type": "Address - Type Changed",
                    "country": "Address - Country Changed",
                    "state": "Address - State Changed"
                },
                "defaultAddress": {
                    "city": "Address - City Changed",
                    "zip": "Address - Zip Code Changed",
                    "streetAddress": "Address - Street Changed",
                    "streetAddress2": "Address - Street2 Changed",
                    "type": "Address - Type Changed",
                    "country": "Address - Country Changed",
                    "state": "Address - State Changed"
                }
            }
        },
        "collection_element_added": {
            "complaint": {
                "addresses.address": "Address Added",
                "personAssociations.personAssociation": "Person Added",
                "organizationAssociations.organizationAssociation": "Organization Added",
                "childObjects": "Association Added",
                "associationsToObjects": "Association Added",
                "associationsFromObjects": "Association Added"
            }
        },
        "collection_element_removed": {
            "complaint": {
                "addresses.address": "Address Removed",
                "personAssociations.personAssociation": "Person Removed",
                "organizationAssociations.organizationAssociation": "Organization Removed",
                "childObjects": "Association Removed",
                "associationsToObjects": "Association Removed",
                "associationsFromObjects": "Association Removed"
            }
        }
    }
}
