{
    "core": {
        "lookups": {
            "common": {
                "home": "Zuhause",
                "other": "Andere",
                "owning-group": "Eigentümergruppe",
                "collaborator": "Mitarbeiter",
                "reader": "Leser",
                "no-access": "Kein Zugang",
                "case": "Fall"
            },
            "addressTypes": {
                "business": "Geschäft"
            },
            "aliasTypes": {
                "fka": "FKA",
                "married": "Verheiratet"
            },
            "personTitles": {
                "mr": "Herr",
                "mrs": "Frau",
                "ms": "Frau",
                "miss": "Fräulein"
            },
            "contactMethodTypes": {
                "phone": "Telefon",
                "work": "Arbeit",
                "mobile": "Mobile",
                "fax": "Fax",
                "email": "Email",
                "personal": "Persönliche",
                "business": "Geschäft",
                "url": "URL",
                "website": "Webseite",
                "facebook": "Facebook",
                "linkedIn": "LinkedIn",
                "twitter": "Twitter"
            },
            "dbasTypes": {
                "dba": "DBA"
            },
            "fileTypes": {
                "ev": "E-Lieferung",
                "gr": "Allgemeine Freigabe",
                "mr": "Medizinische Freigabe",
                "noi": "Beachtenuntersuchung",
                "sig": "SF86 Unterschrift",
                "wir": "Witness Interview Anfrage",
                "draw": "Ingenieur-Zeichnung",
                "other": "Andere"
            },
            "identificationTypes": {
                "ssn": "SSN",
                "driverLicense": "Führerschein",
                "passport": "Reisepass",
                "birthCertificate": "Geburtsurkunde"
            },
            "organizationIdTypes": {
                "ein": "EIN",
                "duns": "DUNS",
                "cageCode": "Käfig-Code"
            },
            "organizationTypes": {
                "non-profit": "Gemeinnützig",
                "government": "Regierung",
                "corporation": "Gesellschaft"
            },
            "organizationalParticipantTypes": {
                "owner": "Eigentümer"
            },
            "entitiesParticipantTypes": {
                "assignee": "Zugewiesen",
                "co-owner": "Mitinhaber",
                "supervisor": "Supervisor",
                "approver": "Genehmiger",
                "follower": "Anhänger"
            },
            "personOrganizationRelationTypes": {
                "owner": "Eigentümer",
                "owned": "Besitz",
                "employee": "Mitarbeiter",
                "employer": "Arbeitgeber",
                "partner": "Partner",
                "director-president-ceo": "Direktor",
                "manager": "Manager",
                "general-counsel": "Rat",
                "executive": "Vorstand"
            },
            "personRelationTypes": {
                "sibling": "Geschwister",
                "children": "Kinder",
                "parent": "Elternteil"
            },
            "organizationRelationTypes": {
                "partner": "Partner",
                "subCompany": "Subunternehmen",
                "parentCompany": "Muttergesellschaft"
            },
            "documentPersonTypes": {
                "defendent": "Beklagte",
                "witness": "Zeuge",
                "was-officer": "WAS Offizier",
                "victim": "Opfer",
                "defense-counsel": "Verteidiger",
                "forensic-scientist": "Forensischer Wissenschaftler"
            },
            "complaintPersonTypes": {
                "initiator": "Initiator",
                "complaintant": "Beschwerdeführer",
                "subject": "Fach",
                "witness": "Zeuge",
                "wrongdoer": "Übeltäter"
            },
            "caseFilePersonTypes": {
                "defendant": "Beklagte",
                "was-officer": "WAS Offizier",
                "victim": "Opfer",
                "defenseCounsel": "Verteidiger",
                "forensicScientist": "Forensischer Wissenschaftler"
            },
            "deviceTypes": {
                "homePhone": "Festnetztelefon",
                "workPhone": "Arbeitshandy",
                "mobile": "Mobile",
                "email": "Email",
                "facebook": "Facebook"
            },
            "priorities": {
                "low": "Niedrig",
                "medium": "Mittel",
                "high": "Hoch",
                "expedite": "Beschleunigen"
            },
            "frequencies": {
                "once": "Einmal",
                "ongoing": "Laufend",
                "intermittent": "Intermittierend"
            },
            "dispositions": {
                "add_existing_case": "Zum vorhandenen Fall hinzufügen",
                "open_investigation": "Offene Untersuchung",
                "no_action": "Keine weiteren Aktionen",
                "refer_external": "Refer Extern"
            },
            "resolutions": {
                "denied": "Verweigert",
                "full": "Voll",
                "partial": "Teilweise"
            },
            "categories": {
                "agricultural": "Landwirtschaftlich",
                "arson": "Brandstiftung",
                "backgroundInvestigation": "Hintergrund Untersuchung",
                "benefits-appeal": "Vorteile Appeal",
                "better-business-dispute": "Besserer Geschäftsstreit",
                "clinical-investigator-fraud": "Klinischer Fahnder",
                "congressionalResponse": "Kongressantwort",
                "disability-waiver-request": "Antrag auf Disability-Waiver",
                "domesticDispute": "Häuslicher Streit",
                "drugTrafficking": "Drogenhandel",
                "education-waiver-request": "Bildungsverzicht",
                "eeo-harassment": "EEO / Belästigung",
                "embezzlement": "Unterschlagung",
                "extortion": "Erpressung",
                "fraud": "Betrug",
                "government": "Regierung",
                "investorComplaint": "Anlegerbeschwerde",
                "laborRacketeering": "Arbeitsverfolgung",
                "local": "Lokal",
                "murder": "Mord",
                "new-drug-application-fraud": "Neue Drogenanwendung Betrug",
                "payoff": "Auszahlen",
                "pension-waiver-request": "Anforderung der Pensionskasse",
                "pollution": "Verschmutzung",
                "productTampering": "Produktmanipulation",
                "theft-or-misuse-of-asset": "Diebstahl oder Missbrauch von Vermögenswerten"
            },
            "caseFileProperties": {
                "id": "Id",
                "caseNumber": "Fallnummer",
                "caseType": "Fallart",
                "title": "Titel",
                "status": "Status",
                "details": "Details",
                "incidentDate": "IncidentDate",
                "created": "Erstellt",
                "creator": "Schöpfer",
                "modified": "Geändert",
                "modifier": "Modifikator",
                "closed": "Abgeschlossen",
                "disposition": "Anordnung",
                "priority": "Priorität",
                "objectType": "Objekttyp"
            },
            "complaintProperties": {
                "complaintId": "ComplaintId",
                "complaintNumber": "Reklamationsnummer",
                "complaintType": "Beschwerde Typ",
                "priority": "Priorität",
                "complaintTitle": "BeschwerdeTitel"
            },
            "complaint.statuses": {
                "draft": "Draft",
                "inapproval": "In Approval",
                "closed": "Closed",
                "Deleted": "Deleted"
            },
            "countries": {
                "AF": "Afghanistan",
                "AX": "Ålandinseln",
                "AL": "Albanien",
                "DZ": "Algerien",
                "AS": "Amerikanischen Samoa-Inseln",
                "AD": "Andorra",
                "AO": "Angola",
                "AI": "Anguilla",
                "AQ": "Antarktis",
                "AG": "Antigua und Barbuda",
                "AR": "Argentinien",
                "AM": "Armenien",
                "AW": "Aruba",
                "AU": "Australien",
                "AT": "Österreich",
                "AZ": "Aserbaidschan",
                "BS": "Bahamas",
                "BH": "Bahrain",
                "BD": "Bangladesch",
                "BB": "Barbados",
                "BY": "Weißrussland",
                "BE": "Belgien",
                "BZ": "Belize",
                "BJ": "Benin",
                "BM": "Bermuda",
                "BT": "Bhutan",
                "BO": "Bolivien",
                "BA": "Bosnien und Herzegowina",
                "BW": "Botswana",
                "BV": "Bouvet-Insel",
                "BR": "Brasilien",
                "IO": "Britisches Territorium des Indischen Ozeans",
                "BN": "Brunei Darussalam",
                "BG": "Bulgarien",
                "BF": "Burkina Faso",
                "BI": "Burundi",
                "KH": "Kambodscha",
                "CM": "Kamerun",
                "CA": "Kanada",
                "CV": "Kap Verde",
                "KY": "Cayman Inseln",
                "CF": "Zentralafrikanische Republik",
                "TD": "Tschad",
                "CL": "Chile",
                "CN": "China",
                "CX": "Weihnachtsinsel",
                "CC": "Kokosinseln",
                "CO": "Kolumbien",
                "KM": "Komoren",
                "CG": "Kongo",
                "CD": "Kongo, die Demokratische Republik",
                "CK": "Cookinseln",
                "CR": "Costa Rica",
                "CI": "Côte d'Ivoire, Republik",
                "HR": "Kroatien",
                "CU": "Kuba",
                "CW": "Curacao",
                "CY": "Zypern",
                "CZ": "Tschechien",
                "DK": "Dänemark",
                "DJ": "Dschibuti",
                "DM": "Dominica",
                "DO": "Dominikanische Republik",
                "EC": "Ecuador",
                "EG": "Ägypten",
                "SV": "El Salvador",
                "GQ": "Äquatorialguinea",
                "ER": "Eritrea",
                "EE": "Estland",
                "ET": "Äthiopien",
                "FK": "Falklandinseln (Malvinas)",
                "FO": "Färöer Inseln",
                "FJ": "Fidschi",
                "FI": "Finnland",
                "FR": "Frankreich",
                "GF": "Französisch-Guayana",
                "PF": "Französisch Polynesien",
                "TF": "Südfranzösische Territorien",
                "GA": "Gabun",
                "GM": "Gambia",
                "GE": "Georgia",
                "DE": "Deutschland",
                "GH": "Ghana",
                "GI": "Gibraltar",
                "GR": "Griechenland",
                "GL": "Grönland",
                "GD": "Grenada",
                "GP": "Guadeloupe",
                "GU": "Guam",
                "GT": "Guatemala",
                "GG": "Guernsey",
                "GN": "Guinea",
                "GW": "Guinea-Bissau",
                "GY": "Guyana",
                "HT": "Haiti",
                "HM": "Heard Island und Mcdonald Islands",
                "VA": "Heiliger Stuhl (Staat Vatikanstadt)",
                "HN": "Honduras",
                "HK": "Hongkong",
                "HU": "Ungarn",
                "IS": "Island",
                "IN": "Indien",
                "ID": "Indonesien",
                "IR": "Iran, Islamische Republik",
                "IQ": "Irak",
                "IE": "Irland",
                "IM": "Isle of Man",
                "IL": "Israel",
                "IT": "Italien",
                "JM": "Jamaika",
                "JP": "Japan",
                "JE": "Jersey",
                "JO": "Jordanien",
                "KZ": "Kasachstan",
                "KE": "Kenia",
                "KI": "Kiribati",
                "KP": "Korea, Demokratische Volksrepublik",
                "KR": "Korea, Republik von",
                "KW": "Kuwait",
                "KG": "Kirgisistan",
                "LA": "Demokratische Volksrepublik Laos",
                "LV": "Lettland",
                "LB": "Libanon",
                "LS": "Lesotho",
                "LR": "Liberia",
                "LY": "Libysch-Arabische Jamahiriya",
                "LI": "Liechtenstein",
                "LT": "Litauen",
                "LU": "Luxemburg",
                "MO": "Macao",
                "MK": "Mazedonien",
                "MG": "Madagaskar",
                "MW": "Malawi",
                "MY": "Malaysia",
                "MV": "Malediven",
                "ML": "Mali",
                "MT": "Malta",
                "MH": "Marshallinseln",
                "MQ": "Martinique",
                "MR": "Mauretanien",
                "MU": "Mauritius",
                "YT": "Mayotte",
                "MX": "Mexiko",
                "FM": "Mikronesien, Föderierte Staaten von",
                "MD": "Moldawien, Republik",
                "MC": "Monaco",
                "MN": "Mongolei",
                "ME": "Montenegro",
                "MS": "Montserrat",
                "MA": "Marokko",
                "MZ": "Mosambik",
                "MM": "Myanmar",
                "NA": "Namibia",
                "NR": "Nauru",
                "NP": "Nepal",
                "NL": "Niederlande",
                "AN": "Niederländische Antillen",
                "NC": "Neu-Kaledonien",
                "NZ": "Neuseeland",
                "NI": "Nicaragua",
                "NE": "Niger",
                "NG": "Nigeria",
                "NU": "Niue",
                "NF": "Norfolkinsel",
                "MP": "Nördliche Marianneninseln",
                "NO": "Norwegen",
                "OM": "Oman",
                "PK": "Pakistan",
                "PW": "Palau",
                "PS": "Besetzte palästinensische Gebiete",
                "PA": "Panama",
                "PG": "Papua Neu-Guinea",
                "PY": "Paraguay",
                "PE": "Peru",
                "PH": "Philippinen",
                "PN": "Pitcairn",
                "PL": "Polen",
                "PT": "Portugal",
                "PR": "Puerto Rico",
                "QA": "Katar",
                "RE": "Wiedervereinigung",
                "RO": "Rumänien",
                "RU": "Russische Föderation",
                "RW": "Ruanda",
                "SH": "Heilige Helena, Himmelfahrt und Tristan da Cunha",
                "KN": "St. Kitts und Nevis",
                "LC": "St. Lucia",
                "PM": "Saint Pierre und Miquelon",
                "VC": "St. Vincent und die Grenadinen",
                "WS": "Samoa",
                "SM": "San Marino",
                "ST": "São Tomé und Príncipe",
                "SA": "Saudi Arabien",
                "SN": "Senegal",
                "RS": "Serbien",
                "SC": "Seychellen",
                "SL": "Sierra Leone",
                "SG": "Singapur",
                "SX": "Sint Maarten",
                "SK": "Slowakei",
                "SI": "Slowenien",
                "SB": "Salomon-Inseln",
                "SO": "Somalia",
                "ZA": "Südafrika",
                "GS": "Südgeorgien und die Südlichen Sandwichinseln",
                "SS": "Südsudan",
                "ES": "Spanien",
                "LK": "Sri Lanka",
                "SD": "Sudan",
                "SR": "Suriname",
                "SJ": "Spitzbergen und Jan Mayen",
                "SZ": "Swasiland",
                "SE": "Schweden",
                "CH": "Schweiz",
                "SY": "Syrische Arabische Republik",
                "TW": "Taiwan, Provinz China",
                "TJ": "Tajikista",
                "TZ": "Tansania, Vereinigte Republik",
                "TH": "Thailand",
                "TL": "Timor-Leste",
                "TG": "Gehen",
                "TK": "Tokelau",
                "TO": "Tonga",
                "TT": "Trinidad und Tobago",
                "TN": "Tunesien",
                "TR": "Truthahn",
                "TM": "Turkmenistan",
                "TC": "Turks- und Caicosinseln",
                "TV": "Tuvalu",
                "UG": "Uganda",
                "UA": "Ukraine",
                "AE": "Vereinigte Arabische Emirate",
                "GB": "Großbritannien",
                "US": "Vereinigte Staaten",
                "UM": "Kleinere Inseln der Vereinigten Staaten",
                "UY": "Uruguay",
                "UZ": "Usbekistan",
                "VU": "Vanuatu",
                "VE": "Venezuela",
                "VN": "Vietnam",
                "VG": "Britische Jungferninseln",
                "VI": "Virgin Islands, U.S.",
                "WF": "Wallis und Futuna",
                "EH": "Westsahara",
                "YE": "Jemen",
                "ZM": "Sambia",
                "ZW": "Simbabwe"
            },
            "costsheet": {
                "titles": {
                    "taxi": "Taxi",
                    "hotel": "Hotel",
                    "overtime": "Im Laufe der Zeit",
                    "food": "Essen"
                }
            },
            "timesheet": {
                "statuses": {
                    "draft": "Entwurf",
                    "inapproval": "In der Genehmigung",
                    "approved": "Genehmigt"
                },
                "other": {
                    "leap": "LEAP",
                    "training": "Ausbildung",
                    "conference": "Konferenz"
                },
                "types": {
                    "case_file": "Fall",
                    "complaint": "Beschwerde"
                }
            },
            "changeCase": {
                "statuses": {
                    "active": "Aktiv",
                    "inactive": "Inaktiv",
                    "closed": "Abgeschlossen",
                    "deleted": "Gelöscht"
                },
                "resolutions": {
                    "denied": "Verweigert",
                    "full": "Voll",
                    "partial": "Teilweise"
                }
            },
            "taskOutcomes": {
                "approve": "Dokument genehmigen",
                "rework": "Zur Nachbesserung senden",
                "resubmit": "Erneut senden",
                "cancel": "Dokument abbrechen",
                "concur": "Samenvallen",
                "nonConcur": "Niet in overeenstemming"
            },
            "businessProcessTypes": {
                "acmDocumentWorkflow": "ACM Dokumenten Arbeitsprozess",
                "correctiveActionPlan": "Korrekturmaßnahmenplan"
            },
            "reportStates": {
                "draft": "Entwurf",
                "inApproval": "Mit Zustimmung",
                "active": "Aktiv",
                "inActive": "Inaktiv",
                "closed": "Geschlossen"
            },
            "auditReportNames": {
                "all": "Alle",
                "case_file": "Fall",
                "complaint": "Beschwerde",
                "task": "Aufgabe",
                "file": "Datei",
                "document": "Dokument",
                "person": "Person",
                "organization": "Organisation"
            }
        },
        "userInfo": {
            "addedMenu": {
                "help": "Hilfe",
                "logout": "Ausloggen"
            }
        },
        "leftNav": {
            "title": "Navigation"
        },
        "topBar": {
            "new": "Neu",
            "toggle.btn": "Navigation umschalten",
            "search.placeholder": "Suche ArkCase",
            "locale.updateList": "Liste oben aktualisieren"
        },
        "loginWarning": {
            "btnOK.text": "Bestätigen",
            "btnCancel.text": "Abbrechen",
            "checkbox_warning.label": "Ich bestätige diese Warnung."
        },
        "unknown": "Unbekannt"
    }
}
