{
    "dashboard": {
        "title": "Dashboard",
        "menus": {
            "leftnav.item": "Dashboard"
        },
        "widgets": {
            "pagination": {
                "default": {
                    "label": "Select your preferred row count.",
                    "fiveRows": "5",
                    "tenRows": "10",
                    "twentyFiveRows": "25"
                }
            },
            "casesByQueue": {
                "title": "Active Case Files by Queue",
                "description": "Displays active case files by queue",
                "xAxis": "Queues",
                "yAxis": "Number of Case Files",
                "noDataMessage": "Currently there are no cases info",
                "configDescription": "Description",
                "configDescriptionPlaceholder": "Enter widget description"
            },
            "casesByStatus": {
                "title": "Cases By Status",
                "description": "Displays cases by status",
                "timePeriod": {
                    "label": "Select Time Period",
                    "lastWeek": "Last Week",
                    "lastMonth": "Last Month",
                    "lastYear": "Last Year",
                    "all": "All"
                },
                "noDataMessage": "Currently there are no cases info",
                "configDescription": "Description",
                "configDescriptionPlaceholder": "Enter widget description"
            },
            "myCases": {
                "title": "My Cases",
                "description": "Displays my cases",
                "noDataMessage": "Currently there are no cases info",
                "table": {
                    "header": {
                        "caseId": "ID",
                        "title": "Title",
                        "priority": "Priority",
                        "created": "Created",
                        "modified": "Modified",
                        "dueDate": "Due Date",
                        "status": "Status",
                        "assignee": "Assignee"
                    },
                    "overdue.tooltip": "Case is Overdue",
                    "deadline.tooltip": "Deadline is Approaching"
                },
                "configDescription": "Description",
                "configDescriptionPlaceholder": "Enter widget description"
            },
            "myComplaints": {
                "title": "My Complaints",
                "description": "Displays my complaints",
                "table": {
                    "header": {
                        "number": "ID",
                        "title": "Title",
                        "priority": "Priority",
                        "created": "Created",
                        "modified": "Modified",
                        "dueDate": "Due Date",
                        "status": "Status",
                        "assignee": "Assignee"
                    },
                    "overdue.tooltip": "Complaint is Overdue",
                    "deadline.tooltip": "Deadline is Approaching",
                    "noDataMessage": "Currently there are no complaints info"
                },
                "configDescription": "Description",
                "configDescriptionPlaceholder": "Enter widget description"
            },
            "myTasks": {
                "title": "My Tasks",
                "description": "Displays my tasks",
                "rowNumbers.label": "Default Row Numbers",
                "rowNumbers.placeholder": "Enter Default Row Numbers",
                "table": {
                    "header": {
                        "taskId": "ID",
                        "title": "Title",
                        "priority": "Priority",
                        "dueDate": "Due",
                        "status": "Status",
                        "objectId": "Object ID"
                    },
                    "overdue.tooltip": "Task is Overdue",
                    "deadline.tooltip": "Deadline is Approaching"
                },
                "noDataMessage": "Currently there are no tasks info",
                "configDescription": "Description",
                "configDescriptionPlaceholder": "Enter widget description"
            },
            "newComplaints": {
                "title": "New Complaints",
                "description": "Displays new complaints",
                "dueDate": {
                    "label": "Select Due Date Period",
                    "pastDue": "Past Due",
                    "dueTomorrow": "Due Tomorrow",
                    "dueWeek": "Due in 7 Days",
                    "dueMonth": "Due in Month",
                    "all": "All"
                },
                "noDataMessage": "Currently there are no complaints info",
                "configDescription": "Description",
                "configDescriptionPlaceholder": "Enter widget description"
            },
            "newCases": {
                "title": "New Cases",
                "description": "Displays new cases",
                "noDataMessage": "Currently there are no cases info",
                "configDescription": "Description",
                "configDescriptionPlaceholder": "Enter widget description"
            },
            "teamWorkload": {
                "title": "Team Workload",
                "description": "Displays team workload",
                "dueDate": {
                    "label": "Select Due Date Period",
                    "pastDue": "Past Due",
                    "dueTomorrow": "Due Tomorrow",
                    "dueWeek": "Due in 7 Days",
                    "dueMonth": "Due in Month",
                    "all": "All"
                },
                "noDataMessage": "Currently there are no team tasks info",
                "configDescription": "Description",
                "configDescriptionPlaceholder": "Enter widget description"
            },
            "workflowReport": {
                "title": "Workflow Report",
                "description": "Displays Workflow Report",
                "rowNumbers.label": "Default Row Numbers",
                "rowNumbers.placeholder": "Enter Default Row Numbers",
                "table": {
                    "header": {
                        "taskId": "Task ID",
                        "taskParentType": "Parent Type",
                        "taskParentName": "Parent Name",
                        "processName": "Business Process Name",
                        "taskName": "Task Name"
                    }
                },
                "noDataMessage": "Currently there is no workflow report info",
                "configDescription": "Description",
                "configDescriptionPlaceholder": "Enter widget description"
            },
            "news": {
                "description": "Displays news",
                "label": {
                    "enterFeedUrl": "Enter Feed url",
                    "description": "Displays a RSS/Atom feed",
                    "feedUrl": "Feed Url",
                    "insertUrl": "Please insert a feed url in the widget configuration"
                },
                "title": "News",
                "noDataMessage": "Currently there is no RSS/info",
                "configDescription": "Description",
                "configDescriptionPlaceholder": "Enter widget description",
                "message": {
                    "error": "Invalid URL"
                }
            },
            "details": {
                "title": "Details",
                "description": "Displays case details",
                "noDataMessage": "Currently there are no details"
            },
            "people": {
                "title": "People",
                "description": "Displays people details",
                "noDataMessage": "Currently there are no people to display"
            },
            "ids": {
                "title": "IDs",
                "description": "Displays IDs details",
                "noDataMessage": "Currently there are no IDs to display"
            },
            "complaints": {
                "title": "Complaints",
                "description": "Displays complaint details",
                "noDataMessage": "Currently there are no complaints to display"
            },
            "cases": {
                "title": "Cases",
                "description": "Displays case details",
                "noDataMessage": "Currently there are no cases to display"
            },
            "documents": {
                "title": "Documents",
                "description": "Displays chart of documents by folder",
                "noDataMessage": "Currently there are no documents to display",
                "series": "Number of Documents"
            },
            "locations": {
                "title": "Locations",
                "description": "Displays location details",
                "noDataMessage": "Currently there are no locations to display"
            },
            "phones": {
                "title": "Phone Numbers",
                "description": "Displays phone numbers",
                "noDataMessage": "Currently there are no phone numbers to display"
            },
            "faxes": {
                "title": "Fax Numbers",
                "description": "Displays faxes details",
                "noDataMessage": "Currently there are no faxes to display"
            },
            "emails": {
                "title": "Email Address",
                "description": "Displays Email details",
                "noDataMessage": "Currently there are no Email addresses to display"
            },
            "urls": {
                "title": "URLs",
                "description": "Displays URLs details",
                "noDataMessage": "Currently there are no URLs to display"
            },
            "dbas": {
                "title": "DBAs",
                "description": "Displays DBA details",
                "noDataMessage": "Currently there are no DBAs to display"
            },
            "tasks": {
                "title": "Tasks",
                "description": "Displays task details",
                "noDataMessage": "Currently there are no tasks to display"
            },
            "participants": {
                "title": "Participants",
                "description": "Displays participant details",
                "noDataMessage": "Currently there are no participant to display"
            },
            "references": {
                "title": "References",
                "description": "Displays reference details",
                "noDataMessage": "Currently there are no references to display"
            },
            "relOrganizations": {
                "title": "Related Organizations",
                "description": "Displays Related Organizations details",
                "noDataMessage": "Currently there are no Related Organizations to display"
            },
            "history": {
                "title": "History",
                "description": "Displays chart of history events",
                "noDataMessage": "Currently there are no events to display"
            },
            "notes": {
                "title": "Notes",
                "description": "Displays note details",
                "noDataMessage": "Currently there are no notes to display"
            },
            "time": {
                "title": "Time",
                "description": "Displays chart for hours per user",
                "noDataMessage": "Currently there is no time information to display"
            },
            "cost": {
                "title": "Cost",
                "description": "Displays chart for cost per user",
                "noDataMessage": "Currently there is no cost information to display"
            },
            "calendar": {
                "title": "Calendar",
                "description": "Displays chart of scheduled events per day",
                "noDataMessage": "Currently there are no events to display",
                "calendarIntegrationDisabledMessage": "Calendar integration is disabled by Administrator"
            },
            "reworkDetails": {
                "title": "Rework Details",
                "description": "Shows most recent rework details",
                "noDataMessage": "Currently there no are no rework details to display"
            },
            "docReview": {
                "title": "Documents Under Review",
                "description": "Shows documents under review",
                "noDataMessage": "Currently there no are no documents under review to display"
            },
            "parentDocs": {
                "title": "Parent Documents",
                "description": "Shows parent documents",
                "noDataMessage": "Currently there no are no parent documents to display"
            },
            "workflow": {
                "title": "Workflow Overview",
                "description": "Overview of pending workflows",
                "noDataMessage": "Currently there are no workflows to display"
            },
            "signature": {
                "title": "eSignature",
                "description": "eSignature widget",
                "noDataMessage": "Currently there are no eSignatures to display"
            },
            "person": {
                "title": "Person",
                "description": "Person widget for Cost and Time modules",
                "noDataMessage": "Currently there are no persons to display"
            },
            "hoursSummary": {
                "title": "Hours Summary",
                "description": "Displays a summary of hours worked",
                "noDataMessage": "Currently there is no summary to display"
            },
            "expenses": {
                "title": "Expenses",
                "description": "Displays a cost-to-user graph",
                "noDataMessage": "Currently no expense data to display"
            },
            "organizations": {
                "title": "Organizations",
                "description": "Displays organization",
                "noDataMessage": "Currently there are no organizations to display"
            },
            "tags": {
                "title": "Tags",
                "description": "Displays Tags",
                "noDataMessage": "Currently there are no tags to display"
            },
            "approvalRouting": {
                "title": "Approval Routing",
                "description": "Displays approval routings",
                "noDataMessage": "Currently no approvers to display"
            },
            "pictures": {
                "title": "Pictures",
                "description": "Display pictures",
                "noDataMessage": "Currently no pictures to display"
            },
            "aliases": {
                "title": "Aliases",
                "description": "Display aliases",
                "noDataMessage": "Currently no aliases to display"
            },
            "related": {
                "title": "Related People",
                "description": "Display related people",
                "noDataMessage": "Currently no related people to display"
            },			
            "approvers": {
                "title": "Approvers",
                "description": "Displays Approvers",
                "noDataMessage": "Currently there are no approvers to display"
            },
            "savePromptModal": {
                "title": "Save dashboard",
                "info": "You are in edit mode. Do you want to save the changes?",
                "save": "Save",
                "doNotSave": "Do not save",
                "cancel": "Cancel"
            }
        }
    },
    "dashboard.comp.news": {
        "title": "News Widget"
    },
    "dashboard.comp.myCases": {
        "title": "My Cases Widget"
    },
    "dashboard.comp.myTasks": {
        "title": "My Tasks Widget"
    },
    "dashboard.comp.myComplaints": {
        "title": "My Complaints Widget"
    },
    "dashboard.comp.workflowReport": {
        "title": "Workflow Report"
    },
    "dashboard.comp.newComplaints": {
        "title": "New Complaints"
    },
    "dashboard.comp.newCases": {
        "title": "New Cases"
    },
    "dashboard.comp.casesByQueue": {
        "title": "Cases By Queue"
    },
    "dashboard.comp.teamWorkload": {
        "title": "Team Workload"
    },
    "dashboard.comp.casesByStatus": {
        "title": "Cases By Status"
    }
}